Metadata-Version: 2.1
Name: autora-experimentalist-assumption
Version: 1.0.0
Summary: Describe your contribution
Author-email: Younes Strittmatter <younes_strittmatter@brown.edu>
License: MIT License
Project-URL: homepage, http://www.empiricalresearch.ai
Project-URL: repository, https://github.com/AutoResearch/autora-experimentalist-assumption
Project-URL: documentation, https://autoresearch.github.io/autora/
Requires-Python: <4,>=3.8
License-File: LICENSE
Requires-Dist: autora-core >=3.1.0
Requires-Dist: scikit-learn
Provides-Extra: dev
Requires-Dist: autora-core[dev] ; extra == 'dev'
